segmentree-0.1.dev12.dist-info/licenses/LICENSE
segtree/__init__.py
segtree/_reader.py
segtree/_sample_data.py
segtree/_version.py
segtree/_widget.py
segtree/_writer.py
segtree/best (1).pt
segtree/napari.yaml
segtree/sam2.1_hq_hiera_l.yaml
segtree/utils.py
segtree/_tests/__init__.py
segtree/_tests/test_reader.py
segtree/_tests/test_sample_data.py
segtree/_tests/test_widget.py
segtree/_tests/test_writer.py
segtree/sam-hq/setup.py
segtree/sam-hq/demo/demo_hqsam.py
segtree/sam-hq/demo/demo_hqsam_light.py
segtree/sam-hq/demo/demo_hqsam_pip_example.py
segtree/sam-hq/demo/demo_sam.py
segtree/sam-hq/sam-hq2/setup.py
segtree/sam-hq/sam-hq2/demo/demo_hqsam2.py
segtree/sam-hq/sam-hq2/sam2/__init__.py
segtree/sam-hq/sam-hq2/sam2/automatic_mask_generator.py
segtree/sam-hq/sam-hq2/sam2/build_sam.py
segtree/sam-hq/sam-hq2/sam2/sam2_hq_video_predictor.py
segtree/sam-hq/sam-hq2/sam2/sam2_image_predictor.py
segtree/sam-hq/sam-hq2/sam2/sam2_video_predictor.py
segtree/sam-hq/sam-hq2/sam2/modeling/__init__.py
segtree/sam-hq/sam-hq2/sam2/modeling/memory_attention.py
segtree/sam-hq/sam-hq2/sam2/modeling/memory_encoder.py
segtree/sam-hq/sam-hq2/sam2/modeling/position_encoding.py
segtree/sam-hq/sam-hq2/sam2/modeling/sam2_base.py
segtree/sam-hq/sam-hq2/sam2/modeling/sam2_hq_base.py
segtree/sam-hq/sam-hq2/sam2/modeling/sam2_utils.py
segtree/sam-hq/sam-hq2/sam2/modeling/backbones/__init__.py
segtree/sam-hq/sam-hq2/sam2/modeling/backbones/hieradet.py
segtree/sam-hq/sam-hq2/sam2/modeling/backbones/image_encoder.py
segtree/sam-hq/sam-hq2/sam2/modeling/backbones/utils.py
segtree/sam-hq/sam-hq2/sam2/modeling/sam/__init__.py
segtree/sam-hq/sam-hq2/sam2/modeling/sam/mask_decoder.py
segtree/sam-hq/sam-hq2/sam2/modeling/sam/mask_hq_decoder.py
segtree/sam-hq/sam-hq2/sam2/modeling/sam/prompt_encoder.py
segtree/sam-hq/sam-hq2/sam2/modeling/sam/transformer.py
segtree/sam-hq/sam-hq2/sam2/utils/__init__.py
segtree/sam-hq/sam-hq2/sam2/utils/amg.py
segtree/sam-hq/sam-hq2/sam2/utils/misc.py
segtree/sam-hq/sam-hq2/sam2/utils/transforms.py
segmentree-0.1.dev12.dist-info/METADATA
segmentree-0.1.dev12.dist-info/WHEEL
segmentree-0.1.dev12.dist-info/entry_points.txt
segmentree-0.1.dev12.dist-info/top_level.txt
segmentree-0.1.dev12.dist-info/RECORD
