Metadata-Version: 2.4
Name: SegmenTree
Version: 0.1.dev12
Summary: Individual tree segmentation
Author: Herearii Metuarea
Author-email: herearii.metuarea@univ-angers.fr
License: 
Project-URL: Bug Tracker, https://github.com/hereariim/segtree/issues
Project-URL: Documentation, https://github.com/hereariim/segtree#README.md
Project-URL: Source Code, https://github.com/hereariim/segtree
Project-URL: User Support, https://github.com/hereariim/segtree/issues
Classifier: Development Status :: 2 - Pre-Alpha
Classifier: Framework :: napari
Classifier: Intended Audience :: Developers
Classifier: License :: OSI Approved :: BSD License
Classifier: Operating System :: OS Independent
Classifier: Programming Language :: Python
Classifier: Programming Language :: Python :: 3
Classifier: Programming Language :: Python :: 3 :: Only
Classifier: Programming Language :: Python :: 3.10
Classifier: Programming Language :: Python :: 3.11
Classifier: Programming Language :: Python :: 3.12
Classifier: Programming Language :: Python :: 3.13
Classifier: Topic :: Scientific/Engineering :: Image Processing
Requires-Python: ==3.10.16
License-File: LICENSE
Requires-Dist: torch>=2.3.1
Requires-Dist: torchvision>=0.18.1
Requires-Dist: numpy
Requires-Dist: magicgui
Requires-Dist: qtpy
Requires-Dist: aiofiles==23.2.1
Requires-Dist: altair==5.5.0
Requires-Dist: annotated-types==0.7.0
Requires-Dist: antlr4-python3-runtime==4.9.3
Requires-Dist: anyio==4.9.0
Requires-Dist: attrs==25.3.0
Requires-Dist: certifi==2025.1.31
Requires-Dist: charset-normalizer==3.4.1
Requires-Dist: click==8.1.8
Requires-Dist: coloredlogs==15.0.1
Requires-Dist: contourpy==1.3.1
Requires-Dist: cycler==0.12.1
Requires-Dist: fastapi==0.115.12
Requires-Dist: ffmpy==0.5.0
Requires-Dist: filelock==3.18.0
Requires-Dist: flatbuffers==25.2.10
Requires-Dist: fonttools==4.56.0
Requires-Dist: fsspec==2025.3.2
Requires-Dist: gradio==4.29.0
Requires-Dist: gradio-client==0.16.1
Requires-Dist: gradio-imageslider==0.0.20
Requires-Dist: h11==0.14.0
Requires-Dist: httpcore==1.0.7
Requires-Dist: httpx==0.28.1
Requires-Dist: huggingface-hub==0.30.1
Requires-Dist: humanfriendly==10.0
Requires-Dist: hydra-core==1.3.2
Requires-Dist: idna==3.10
Requires-Dist: imageio==2.37.0
Requires-Dist: importlib-resources==6.5.2
Requires-Dist: iopath==0.1.10
Requires-Dist: jinja2==3.1.6
Requires-Dist: joblib==1.4.2
Requires-Dist: jsonschema==4.23.0
Requires-Dist: jsonschema-specifications==2024.10.1
Requires-Dist: kiwisolver==1.4.8
Requires-Dist: lazy-loader==0.4
Requires-Dist: markdown-it-py==3.0.0
Requires-Dist: markupsafe==2.1.5
Requires-Dist: matplotlib==3.10.1
Requires-Dist: mdurl==0.1.2
Requires-Dist: mpmath==1.3.0
Requires-Dist: narwhals==1.33.0
Requires-Dist: networkx==3.4.2
Requires-Dist: numpy==1.26.4
Requires-Dist: omegaconf==2.3.0
Requires-Dist: onnx==1.17.0
Requires-Dist: onnxruntime==1.21.0
Requires-Dist: opencv-python==4.11.0.86
Requires-Dist: orjson==3.10.16
Requires-Dist: pandas==2.2.3
Requires-Dist: pillow==10.4.0
Requires-Dist: portalocker==3.1.1
Requires-Dist: protobuf==6.30.2
Requires-Dist: py-cpuinfo==9.0.0
Requires-Dist: pycocotools==2.0.8
Requires-Dist: pydantic==2.11.1
Requires-Dist: pydantic-core==2.33.0
Requires-Dist: pydub==0.25.1
Requires-Dist: pyparsing==3.2.3
Requires-Dist: pyreadline3==3.5.4
Requires-Dist: python-multipart==0.0.20
Requires-Dist: pytz==2025.2
Requires-Dist: pywin32==310
Requires-Dist: pyyaml==6.0.2
Requires-Dist: referencing==0.36.2
Requires-Dist: regex==2024.11.6
Requires-Dist: requests==2.32.3
Requires-Dist: rich==14.0.0
Requires-Dist: rpds-py==0.24.0
Requires-Dist: ruff==0.11.2
Requires-Dist: safetensors==0.5.3
Requires-Dist: scikit-image==0.25.2
Requires-Dist: scikit-learn==1.6.1
Requires-Dist: scipy==1.15.2
Requires-Dist: seaborn==0.13.2
Requires-Dist: semantic-version==2.10.0
Requires-Dist: shellingham==1.5.4
Requires-Dist: sniffio==1.3.1
Requires-Dist: starlette==0.46.1
Requires-Dist: sympy==1.13.1
Requires-Dist: threadpoolctl==3.6.0
Requires-Dist: tifffile==2025.3.30
Requires-Dist: timm==1.0.15
Requires-Dist: tokenizers==0.21.1
Requires-Dist: tomlkit==0.12.0
Requires-Dist: tqdm==4.67.1
Requires-Dist: transformers==4.50.3
Requires-Dist: typer==0.15.2
Requires-Dist: typing-inspection==0.4.0
Requires-Dist: tzdata==2025.2
Requires-Dist: ultralytics==8.3.99
Requires-Dist: ultralytics-thop==2.0.14
Requires-Dist: urllib3==2.3.0
Requires-Dist: uvicorn==0.34.0
Requires-Dist: websockets==11.0.3
Provides-Extra: testing
Requires-Dist: tox; extra == "testing"
Requires-Dist: pytest; extra == "testing"
Requires-Dist: pytest-cov; extra == "testing"
Requires-Dist: pytest-qt; extra == "testing"
Requires-Dist: napari; extra == "testing"
Requires-Dist: pyqt5; extra == "testing"
Dynamic: license-file
